ibp_python_sdk/__init__.py
ibp_python_sdk/blockchain_v3.py
ibp_python_sdk/common.py
ibp_python_sdk/version.py
ibp_python_sdk-0.1.2.dist-info/LICENSE
ibp_python_sdk-0.1.2.dist-info/METADATA
ibp_python_sdk-0.1.2.dist-info/WHEEL
ibp_python_sdk-0.1.2.dist-info/top_level.txt
ibp_python_sdk-0.1.2.dist-info/RECORD
