Metadata-Version: 2.1
Name: ibp-python-sdk
Version: 0.1.2
Summary: Python client library for IBM Blockchain Platform
Home-page: https://github.com/IBM-Blockchain/ibp-python-sdk
Author: IBM
Author-email: no-reply@ibm.com
License: Apache 2.0
Keywords: ibp-python-sdk
Platform: UNKNOWN
Classifier: Programming Language :: Python
Classifier: Programming Language :: Python :: 3
Classifier: Programming Language :: Python :: 3.5
Classifier: Programming Language :: Python :: 3.6
Classifier: Programming Language :: Python :: 3.7
Classifier: Programming Language :: Python :: 3.8
Classifier: Intended Audience :: Developers
Classifier: License :: OSI Approved :: Apache Software License
Classifier: Operating System :: OS Independent
Classifier: Topic :: Software Development :: Libraries :: Python Modules
Classifier: Topic :: Software Development :: Libraries :: Application Frameworks
Requires-Python: >=3.5
